gorgon/__init__.py
gorgon/cluster_run.py
gorgon/gorgon.py
gorgon/report.py
gorgon-0.3.4.dist-info/DESCRIPTION.rst
gorgon-0.3.4.dist-info/METADATA
gorgon-0.3.4.dist-info/metadata.json
gorgon-0.3.4.dist-info/RECORD
gorgon-0.3.4.dist-info/top_level.txt
gorgon-0.3.4.dist-info/WHEEL
