Metadata-Version: 2.0
Name: gorgon
Version: 0.3.4
Summary: A simple multiplier task analysis tool in Python
Home-page: https://github.com/jaimebuelta/gorgon
Author: Jaime Buelta
Author-email: jaime.buelta@gmail.com
License: MIT
Download-URL: https://github.com/jaimebuelta/gorgon/tarball/0.3.4
Keywords: multiprocess,multithread,analysis
Platform: Cross Platform
Classifier: Programming Language :: Python :: 2
Classifier: Programming Language :: Python :: 3
Requires-Dist: paramiko
